{
  "Augment Immune": {
    "Weapon": [
      {
        "name": "Violent Sledgehammer",
        "mainStat": "ATK%"
      }
    ],
    "Amulet": [
      {
        "name": "Death's Hold",
        "mainStat": "PEN%"
      }
    ],
    "Set": [
      "ag2i2"
    ],
    "SubstatPrio": "ATK>CHC>CHD>SPD",
    "Note": "",
    "Talisman": [
      "$CPdps"
    ]
  },
  "Counter Immune": {
    "Weapon": [
      {
        "name": "Violent Sledgehammer",
        "mainStat": "ATK%"
      }
    ],
    "Amulet": [
      {
        "name": "Death's Hold",
        "mainStat": "PEN%"
      }
    ],
    "Set": [
      "i2ct2"
    ],
    "SubstatPrio": "ATK>CHC>CHD>SPD",
    "Note": "",
    "Talisman": [
      "$CPdps"
    ]
  },
  "Speed": {
    "Weapon": [
      {
        "name": "Violent Sledgehammer",
        "mainStat": "ATK%"
      }
    ],
    "Amulet": [
      {
        "name": "Death's Hold",
        "mainStat": "PEN%"
      }
    ],
    "Set": [
      "s4"
    ],
    "SubstatPrio": "ATK>CHC>CHD>SPD",
    "Note": "",
    "Talisman": [
      "$CPdps"
    ]
  },
  "High Crit": {
    "Weapon": [
      {
        "name": "Violent Sledgehammer",
        "mainStat": "ATK%"
      }
    ],
    "Amulet": [
      {
        "name": "Death's Hold",
        "mainStat": "PEN%"
      }
    ],
    "Set": [
      "chd4"
    ],
    "SubstatPrio": "ATK>CHC>CHD>SPD",
    "Note": "",
    "Talisman": [
      "$CPdps"
    ]
  }
}
