{
  "floors": [
    {
      "floor": 1,
      "boss_id": "5010007",
      "minions": [
        "5010001",
        "5010003"
      ]
    },
    {
      "floor": 2,
      "boss_id": "5010107",
      "minions": [
        "5010101",
        "5010102",
        "5010103"
      ]
    },
    {
      "floor": 3,
      "boss_id": "5010207",
      "minions": [
        "5010202",
        "5010201",
        "5010203"
      ]
    },
    {
      "floor": 4,
      "boss_id": "5010008",
      "minions": [
        "5010104",
        "5010204",
        "5010004"
      ]
    },
    {
      "floor": 5,
      "boss_id": "62000061",
      "minions": [
        "52000001",
        "52000030"
      ]
    },
    {
      "floor": 6,
      "boss_id": "5010108",
      "minions": [
        "5010101",
        "5010103"
      ]
    },
    {
      "floor": 7,
      "boss_id": "5010207",
      "minions": [
        "52000032",
        "5010202"
      ]
    },
    {
      "floor": 8,
      "boss_id": "62000017",
      "minions": [
        "5010101",
        "5010104"
      ]
    },
    {
      "floor": 9,
      "boss_id": "62000049",
      "minions": [
        "5010003",
        "5010005",
        "5010006"
      ]
    },
    {
      "floor": 10,
      "boss_id": "5011001",
      "minions": [
        "52000004",
        "52000005"
      ]
    },
    {
      "floor": 11,
      "boss_id": "5011007",
      "minions": [
        "5010001",
        "5010003"
      ]
    },
    {
      "floor": 12,
      "boss_id": "5011107",
      "minions": [
        "5010101",
        "5010102"
      ]
    },
    {
      "floor": 13,
      "boss_id": "5011207",
      "minions": [
        "5010203",
        "5010201"
      ]
    },
    {
      "floor": 14,
      "boss_id": "62000005",
      "minions": [
        "5010104",
        "52000012"
      ]
    },
    {
      "floor": 15,
      "boss_id": "62000034",
      "minions": [
        "52000032",
        "52000049"
      ]
    },
    {
      "floor": 16,
      "boss_id": "5011008",
      "minions": [
        "5010004",
        "52000032"
      ]
    },
    {
      "floor": 17,
      "boss_id": "5011108",
      "minions": [
        "52000030",
        "52000005",
        "52000004"
      ]
    },
    {
      "floor": 18,
      "boss_id": "5010208",
      "minions": [
        "52000058",
        "52000024"
      ]
    },
    {
      "floor": 19,
      "boss_id": "62000055",
      "minions": [
        "52000030",
        "52000034",
        "52000062"
      ]
    },
    {
      "floor": 20,
      "boss_id": "5011002"
    },
    {
      "floor": 21,
      "boss_id": "62000012",
      "minions": [
        "52000001",
        "52000032"
      ]
    },
    {
      "floor": 22,
      "boss_id": "62001017",
      "minions": [
        "5010104",
        "52000043"
      ]
    },
    {
      "floor": 23,
      "boss_id": "62000024",
      "minions": [
        "5010005",
        "5010006",
        "52000036"
      ]
    },
    {
      "floor": 24,
      "boss_id": "62000030",
      "minions": [
        "5010201",
        "5010203",
        "52000017"
      ]
    },
    {
      "floor": 25,
      "boss_id": "62000058",
      "minions": [
        "52000024",
        "52000017",
        "52000036"
      ]
    },
    {
      "floor": 26,
      "boss_id": "62000036",
      "minions": [
        "5010204",
        "52000005",
        "5010003"
      ]
    },
    {
      "floor": 27,
      "boss_id": "62000040",
      "minions": [
        "5010103",
        "5010204",
        "52000061"
      ]
    },
    {
      "floor": 28,
      "boss_id": "62000043",
      "minions": [
        "5010103",
        "5010102",
        "52000055"
      ]
    },
    {
      "floor": 29,
      "boss_id": "62001049",
      "minions": [
        "5010003",
        "52000062",
        "5010204"
      ]
    },
    {
      "floor": 30,
      "boss_id": "5012001"
    },
    {
      "floor": 31,
      "boss_id": "62000004",
      "minions": [
        "52000001",
        "52000036"
      ]
    },
    {
      "floor": 32,
      "boss_id": "62002049",
      "minions": [
        "52000049",
        "52000043"
      ]
    },
    {
      "floor": 33,
      "boss_id": "62001012",
      "minions": [
        "5010206"
      ]
    },
    {
      "floor": 34,
      "boss_id": "62001034",
      "minions": [
        "52000062",
        "52000024",
        "52000004"
      ]
    },
    {
      "floor": 35,
      "boss_id": "62001055",
      "minions": [
        "52000001",
        "52000043",
        "52000032"
      ]
    },
    {
      "floor": 36,
      "boss_id": "62001043",
      "minions": [
        "5010006",
        "5010005"
      ]
    },
    {
      "floor": 37,
      "boss_id": "62001058",
      "minions": [
        "5010205",
        "5010206"
      ]
    },
    {
      "floor": 38,
      "boss_id": "62001061",
      "minions": [
        "5010104",
        "5010106"
      ]
    },
    {
      "floor": 39,
      "boss_id": "62000062",
      "minions": [
        "5010203",
        "5010204",
        "5010205"
      ]
    },
    {
      "floor": 40,
      "boss_id": "5011003"
    },
    {
      "floor": 41,
      "boss_id": "62001032",
      "minions": [
        "52000030",
        "52000024"
      ]
    },
    {
      "floor": 42,
      "boss_id": "62001040",
      "minions": [
        "5010001",
        "5010003"
      ]
    },
    {
      "floor": 43,
      "boss_id": "62000001",
      "minions": [
        "52000055",
        "52000036"
      ]
    },
    {
      "floor": 44,
      "boss_id": "62002043",
      "minions": [
        "52000043"
      ]
    },
    {
      "floor": 45,
      "boss_id": "62002061",
      "minions": [
        "52000012",
        "52000055",
        "52000058"
      ]
    },
    {
      "floor": 46,
      "boss_id": "62003043",
      "minions": [
        "52000040",
        "52000062",
        "52000036"
      ]
    },
    {
      "floor": 47,
      "boss_id": "62002058",
      "minions": [
        "52000024",
        "52000036",
        "52000017"
      ]
    },
    {
      "floor": 48,
      "boss_id": "62003061",
      "minions": [
        "52000032",
        "52000005",
        "52000043"
      ]
    },
    {
      "floor": 49,
      "boss_id": "62001062",
      "minions": [
        "52000040",
        "52000034"
      ]
    },
    {
      "floor": 50,
      "boss_id": "5011004"
    },
    {
      "floor": 51,
      "boss_id": "5010008",
      "minions": [
        "5010104",
        "5010204",
        "5010004"
      ]
    },
    {
      "floor": 52,
      "boss_id": "5010207",
      "minions": [
        "5010202",
        "5010201",
        "5010203"
      ]
    },
    {
      "floor": 53,
      "boss_id": "5010107",
      "minions": [
        "5010101",
        "5010102",
        "5010103"
      ]
    },
    {
      "floor": 54,
      "boss_id": "5010007",
      "minions": [
        "5010001",
        "5010003"
      ]
    },
    {
      "floor": 55,
      "boss_id": "62005013",
      "minions": [
        "52000032",
        "52000049"
      ]
    },
    {
      "floor": 56,
      "boss_id": "62000049",
      "minions": [
        "5010003",
        "5010005",
        "5010006"
      ]
    },
    {
      "floor": 57,
      "boss_id": "62000017",
      "minions": [
        "5010101",
        "5010104"
      ]
    },
    {
      "floor": 58,
      "boss_id": "5010207",
      "minions": [
        "52000032",
        "5010202"
      ]
    },
    {
      "floor": 59,
      "boss_id": "5010108",
      "minions": [
        "5010101",
        "5010103"
      ]
    },
    {
      "floor": 60,
      "boss_id": "62005008",
      "minions": [
        "62005001",
        "62005002"
      ]
    },
    {
      "floor": 61,
      "boss_id": "5011008",
      "minions": [
        "5010004",
        "52000032"
      ]
    },
    {
      "floor": 62,
      "boss_id": "5011108",
      "minions": [
        "52000030",
        "52000005",
        "52000004"
      ]
    },
    {
      "floor": 63,
      "boss_id": "5010208",
      "minions": [
        "52000058",
        "52000024"
      ]
    },
    {
      "floor": 64,
      "boss_id": "62000055",
      "minions": [
        "52000030",
        "52000034",
        "52000062"
      ]
    },
    {
      "floor": 65,
      "boss_id": "62005014",
      "minions": [
        "52000001",
        "52000030"
      ]
    },
    {
      "floor": 66,
      "boss_id": "5011007",
      "minions": [
        "5010001",
        "5010003"
      ]
    },
    {
      "floor": 67,
      "boss_id": "5011107",
      "minions": [
        "5010101",
        "5010102"
      ]
    },
    {
      "floor": 68,
      "boss_id": "5011207",
      "minions": [
        "5010203",
        "5010201"
      ]
    },
    {
      "floor": 69,
      "boss_id": "62000005",
      "minions": [
        "5010104",
        "52000012"
      ]
    },
    {
      "floor": 70,
      "boss_id": "62005009",
      "minions": [
        "62005003",
        "62005004",
        "62005005"
      ]
    },
    {
      "floor": 71,
      "boss_id": "62000036",
      "minions": [
        "5010204",
        "52000005",
        "5010003"
      ]
    },
    {
      "floor": 72,
      "boss_id": "62000040",
      "minions": [
        "5010103",
        "5010204",
        "52000061"
      ]
    },
    {
      "floor": 73,
      "boss_id": "62000043",
      "minions": [
        "5010103",
        "5010102",
        "52000055"
      ]
    },
    {
      "floor": 74,
      "boss_id": "62001049",
      "minions": [
        "5010003",
        "52000062",
        "5010204"
      ]
    },
    {
      "floor": 75,
      "boss_id": "62005015",
      "minions": [
        "52000024",
        "52000017",
        "52000036"
      ]
    },
    {
      "floor": 76,
      "boss_id": "62000012",
      "minions": [
        "52000001",
        "52000032"
      ]
    },
    {
      "floor": 77,
      "boss_id": "62001017",
      "minions": [
        "5010104",
        "52000043"
      ]
    },
    {
      "floor": 78,
      "boss_id": "62000024",
      "minions": [
        "5010005",
        "5010006",
        "52000036"
      ]
    },
    {
      "floor": 79,
      "boss_id": "62000030",
      "minions": [
        "5010201",
        "5010203",
        "52000017"
      ]
    },
    {
      "floor": 80,
      "boss_id": "62005010",
      "minions": [
        "62005006",
        "62005007"
      ]
    },
    {
      "floor": 81,
      "boss_id": "62001043",
      "minions": [
        "5010006",
        "5010005"
      ]
    },
    {
      "floor": 82,
      "boss_id": "62001058",
      "minions": [
        "5010205",
        "5010206"
      ]
    },
    {
      "floor": 83,
      "boss_id": "62001061",
      "minions": [
        "5010104",
        "5010106"
      ]
    },
    {
      "floor": 84,
      "boss_id": "62000062",
      "minions": [
        "5010203",
        "5010204",
        "5010205"
      ]
    },
    {
      "floor": 85,
      "boss_id": "62005016",
      "minions": [
        "52000012",
        "52000055",
        "52000058"
      ]
    },
    {
      "floor": 86,
      "boss_id": "62000004",
      "minions": [
        "52000001",
        "52000036"
      ]
    },
    {
      "floor": 87,
      "boss_id": "62002049",
      "minions": [
        "52000049",
        "52000043"
      ]
    },
    {
      "floor": 88,
      "boss_id": "62001012",
      "minions": [
        "5010206"
      ]
    },
    {
      "floor": 89,
      "boss_id": "62001034",
      "minions": [
        "52000062",
        "52000024",
        "52000004"
      ]
    },
    {
      "floor": 90,
      "boss_id": "62005011"
    },
    {
      "floor": 91,
      "boss_id": "62003043",
      "minions": [
        "52000040",
        "52000062",
        "52000036"
      ]
    },
    {
      "floor": 92,
      "boss_id": "62002058",
      "minions": [
        "52000024",
        "52000036",
        "52000017"
      ]
    },
    {
      "floor": 93,
      "boss_id": "62003061",
      "minions": [
        "52000032",
        "52000005",
        "52000043"
      ]
    },
    {
      "floor": 94,
      "boss_id": "62001062",
      "minions": [
        "52000040",
        "52000034"
      ]
    },
    {
      "floor": 95,
      "boss_id": "62005017",
      "minions": [
        "52000001",
        "52000043",
        "52000032"
      ]
    },
    {
      "floor": 96,
      "boss_id": "62001032",
      "minions": [
        "52000030",
        "52000024"
      ]
    },
    {
      "floor": 97,
      "boss_id": "62001040",
      "minions": [
        "5010001",
        "5010003"
      ]
    },
    {
      "floor": 98,
      "boss_id": "62000001",
      "minions": [
        "52000055",
        "52000036"
      ]
    },
    {
      "floor": 99,
      "boss_id": "62002043",
      "minions": [
        "52000043"
      ]
    },
    {
      "floor": 100,
      "boss_id": "62005012"
    }
  ]
}