{
  "id": "401101191",
  "Name": {
    "en": "Reptil Sword-Wielder",
    "kr": "렙틸 소드",
    "jp": "ソード・レプタイル",
    "zh": "剑士蜥蜴人"
  },
  "Surname": null,
  "IncludeSurname": false,
  "class": "Defender",
  "element": "Water",
  "level": 30,
  "icons": "4011011",
  "BuffImmune": "",
  "StatBuffImmune": "ATTACK",
  "location": {
    "dungeon": {
      "en": "",
      "kr": "",
      "jp": "",
      "zh": ""
    },
    "mode": {
      "en": "",
      "kr": "",
      "jp": "",
      "zh": ""
    },
    "area_id": null
  },
  "skills": [
    {
      "name": {
        "en": "Slice",
        "kr": "가르기",
        "jp": "切り裂き",
        "zh": "劈裂"
      },
      "type": "SKT_FIRST",
      "description": {
        "en": "Attacks an enemy.\\nThis attack penetrates <color=#28d9ed>15%</color> of the target's Defense.",
        "kr": "적을 공격합니다.\\n해당 공격 시 관통력이 <color=#28d9ed>15%</color>증가합니다.",
        "jp": "敵単体にダメージを与える。\\nこのスキルは、貫通力が<color=#28d9ed>15%</color>UPする。",
        "zh": "攻击敌人。\\n发动该技能时,穿透力提升<color=#28d9ed>15%</color>。"
      },
      "icon": "MT_Attack_Sword_1_Fire"
    }
  ]
}