[
  {
    "ID": "1",
    "GuildRaidID": "1",
    "NeedPoint": "5490000",
    "RewardID": "3702001"
  },
  {
    "ID": "2",
    "GuildRaidID": "1",
    "NeedPoint": "17140000",
    "RewardID": "3702002"
  },
  {
    "ID": "3",
    "GuildRaidID": "1",
    "NeedPoint": "34280000",
    "RewardID": "3702003"
  },
  {
    "ID": "4",
    "GuildRaidID": "1",
    "NeedPoint": "68550000",
    "RewardID": "3702004"
  },
  {
    "ID": "5",
    "GuildRaidID": "1",
    "NeedPoint": "102820000",
    "RewardID": "3702005"
  },
  {
    "ID": "6",
    "GuildRaidID": "1",
    "NeedPoint": "137090000",
    "RewardID": "3702006"
  },
  {
    "ID": "7",
    "GuildRaidID": "1",
    "NeedPoint": "171360000",
    "RewardID": "3702007"
  },
  {
    "ID": "8",
    "GuildRaidID": "1",
    "NeedPoint": "205640000",
    "RewardID": "3702008"
  },
  {
    "ID": "9",
    "GuildRaidID": "1",
    "NeedPoint": "257040000",
    "RewardID": "3702009"
  },
  {
    "ID": "10",
    "GuildRaidID": "1",
    "NeedPoint": "342720000",
    "RewardID": "3702010"
  },
  {
    "ID": "11",
    "GuildRaidID": "2",
    "NeedPoint": "2310000",
    "RewardID": "3702001"
  },
  {
    "ID": "12",
    "GuildRaidID": "2",
    "NeedPoint": "7200000",
    "RewardID": "3702002"
  },
  {
    "ID": "13",
    "GuildRaidID": "2",
    "NeedPoint": "14400000",
    "RewardID": "3702003"
  },
  {
    "ID": "14",
    "GuildRaidID": "2",
    "NeedPoint": "28800000",
    "RewardID": "3702004"
  },
  {
    "ID": "15",
    "GuildRaidID": "2",
    "NeedPoint": "43200000",
    "RewardID": "3702005"
  },
  {
    "ID": "16",
    "GuildRaidID": "2",
    "NeedPoint": "57600000",
    "RewardID": "3702006"
  },
  {
    "ID": "17",
    "GuildRaidID": "2",
    "NeedPoint": "72000000",
    "RewardID": "3702007"
  },
  {
    "ID": "18",
    "GuildRaidID": "2",
    "NeedPoint": "86400000",
    "RewardID": "3702008"
  },
  {
    "ID": "19",
    "GuildRaidID": "2",
    "NeedPoint": "108000000",
    "RewardID": "3702009"
  },
  {
    "ID": "20",
    "GuildRaidID": "2",
    "NeedPoint": "144000000",
    "RewardID": "3702010"
  },
  {
    "ID": "21",
    "GuildRaidID": "3",
    "NeedPoint": "2310000",
    "RewardID": "3702001"
  },
  {
    "ID": "22",
    "GuildRaidID": "3",
    "NeedPoint": "7200000",
    "RewardID": "3702002"
  },
  {
    "ID": "23",
    "GuildRaidID": "3",
    "NeedPoint": "14400000",
    "RewardID": "3702003"
  },
  {
    "ID": "24",
    "GuildRaidID": "3",
    "NeedPoint": "28800000",
    "RewardID": "3702004"
  },
  {
    "ID": "25",
    "GuildRaidID": "3",
    "NeedPoint": "43200000",
    "RewardID": "3702005"
  },
  {
    "ID": "26",
    "GuildRaidID": "3",
    "NeedPoint": "57600000",
    "RewardID": "3702006"
  },
  {
    "ID": "27",
    "GuildRaidID": "3",
    "NeedPoint": "72000000",
    "RewardID": "3702007"
  },
  {
    "ID": "28",
    "GuildRaidID": "3",
    "NeedPoint": "86400000",
    "RewardID": "3702008"
  },
  {
    "ID": "29",
    "GuildRaidID": "3",
    "NeedPoint": "108000000",
    "RewardID": "3702009"
  },
  {
    "ID": "30",
    "GuildRaidID": "3",
    "NeedPoint": "144000000",
    "RewardID": "3702010"
  },
  {
    "ID": "31",
    "GuildRaidID": "4",
    "NeedPoint": "2310000",
    "RewardID": "3702001"
  },
  {
    "ID": "32",
    "GuildRaidID": "4",
    "NeedPoint": "7200000",
    "RewardID": "3702002"
  },
  {
    "ID": "33",
    "GuildRaidID": "4",
    "NeedPoint": "14400000",
    "RewardID": "3702003"
  },
  {
    "ID": "34",
    "GuildRaidID": "4",
    "NeedPoint": "28800000",
    "RewardID": "3702004"
  },
  {
    "ID": "35",
    "GuildRaidID": "4",
    "NeedPoint": "43200000",
    "RewardID": "3702005"
  },
  {
    "ID": "36",
    "GuildRaidID": "4",
    "NeedPoint": "57600000",
    "RewardID": "3702006"
  },
  {
    "ID": "37",
    "GuildRaidID": "4",
    "NeedPoint": "72000000",
    "RewardID": "3702007"
  },
  {
    "ID": "38",
    "GuildRaidID": "4",
    "NeedPoint": "86400000",
    "RewardID": "3702008"
  },
  {
    "ID": "39",
    "GuildRaidID": "4",
    "NeedPoint": "108000000",
    "RewardID": "3702009"
  },
  {
    "ID": "40",
    "GuildRaidID": "4",
    "NeedPoint": "144000000",
    "RewardID": "3702010"
  },
  {
    "ID": "41",
    "GuildRaidID": "5",
    "NeedPoint": "2310000",
    "RewardID": "3702001"
  },
  {
    "ID": "42",
    "GuildRaidID": "5",
    "NeedPoint": "7200000",
    "RewardID": "3702002"
  },
  {
    "ID": "43",
    "GuildRaidID": "5",
    "NeedPoint": "14400000",
    "RewardID": "3702003"
  },
  {
    "ID": "44",
    "GuildRaidID": "5",
    "NeedPoint": "28800000",
    "RewardID": "3702004"
  },
  {
    "ID": "45",
    "GuildRaidID": "5",
    "NeedPoint": "43200000",
    "RewardID": "3702005"
  },
  {
    "ID": "46",
    "GuildRaidID": "5",
    "NeedPoint": "57600000",
    "RewardID": "3702006"
  },
  {
    "ID": "47",
    "GuildRaidID": "5",
    "NeedPoint": "72000000",
    "RewardID": "3702007"
  },
  {
    "ID": "48",
    "GuildRaidID": "5",
    "NeedPoint": "86400000",
    "RewardID": "3702008"
  },
  {
    "ID": "49",
    "GuildRaidID": "5",
    "NeedPoint": "108000000",
    "RewardID": "3702009"
  },
  {
    "ID": "50",
    "GuildRaidID": "5",
    "NeedPoint": "144000000",
    "RewardID": "3702010"
  },
  {
    "ID": "51",
    "GuildRaidID": "6",
    "NeedPoint": "2310000",
    "RewardID": "3702001"
  },
  {
    "ID": "52",
    "GuildRaidID": "6",
    "NeedPoint": "7200000",
    "RewardID": "3702002"
  },
  {
    "ID": "53",
    "GuildRaidID": "6",
    "NeedPoint": "14400000",
    "RewardID": "3702003"
  },
  {
    "ID": "54",
    "GuildRaidID": "6",
    "NeedPoint": "28800000",
    "RewardID": "3702004"
  },
  {
    "ID": "55",
    "GuildRaidID": "6",
    "NeedPoint": "43200000",
    "RewardID": "3702005"
  },
  {
    "ID": "56",
    "GuildRaidID": "6",
    "NeedPoint": "57600000",
    "RewardID": "3702006"
  },
  {
    "ID": "57",
    "GuildRaidID": "6",
    "NeedPoint": "72000000",
    "RewardID": "3702007"
  },
  {
    "ID": "58",
    "GuildRaidID": "6",
    "NeedPoint": "86400000",
    "RewardID": "3702008"
  },
  {
    "ID": "59",
    "GuildRaidID": "6",
    "NeedPoint": "108000000",
    "RewardID": "3702009"
  },
  {
    "ID": "60",
    "GuildRaidID": "6",
    "NeedPoint": "144000000",
    "RewardID": "3702010"
  },
  {
    "ID": "61",
    "GuildRaidID": "7",
    "NeedPoint": "2310000",
    "RewardID": "3702001"
  },
  {
    "ID": "62",
    "GuildRaidID": "7",
    "NeedPoint": "7200000",
    "RewardID": "3702002"
  },
  {
    "ID": "63",
    "GuildRaidID": "7",
    "NeedPoint": "14400000",
    "RewardID": "3702003"
  },
  {
    "ID": "64",
    "GuildRaidID": "7",
    "NeedPoint": "28800000",
    "RewardID": "3702004"
  },
  {
    "ID": "65",
    "GuildRaidID": "7",
    "NeedPoint": "43200000",
    "RewardID": "3702005"
  },
  {
    "ID": "66",
    "GuildRaidID": "7",
    "NeedPoint": "57600000",
    "RewardID": "3702006"
  },
  {
    "ID": "67",
    "GuildRaidID": "7",
    "NeedPoint": "72000000",
    "RewardID": "3702007"
  },
  {
    "ID": "68",
    "GuildRaidID": "7",
    "NeedPoint": "86400000",
    "RewardID": "3702008"
  },
  {
    "ID": "69",
    "GuildRaidID": "7",
    "NeedPoint": "108000000",
    "RewardID": "3702009"
  },
  {
    "ID": "70",
    "GuildRaidID": "7",
    "NeedPoint": "144000000",
    "RewardID": "3702010"
  },
  {
    "ID": "71",
    "GuildRaidID": "8",
    "NeedPoint": "2310000",
    "RewardID": "3702001"
  },
  {
    "ID": "72",
    "GuildRaidID": "8",
    "NeedPoint": "7200000",
    "RewardID": "3702002"
  },
  {
    "ID": "73",
    "GuildRaidID": "8",
    "NeedPoint": "14400000",
    "RewardID": "3702003"
  },
  {
    "ID": "74",
    "GuildRaidID": "8",
    "NeedPoint": "28800000",
    "RewardID": "3702004"
  },
  {
    "ID": "75",
    "GuildRaidID": "8",
    "NeedPoint": "43200000",
    "RewardID": "3702005"
  },
  {
    "ID": "76",
    "GuildRaidID": "8",
    "NeedPoint": "57600000",
    "RewardID": "3702006"
  },
  {
    "ID": "77",
    "GuildRaidID": "8",
    "NeedPoint": "72000000",
    "RewardID": "3702007"
  },
  {
    "ID": "78",
    "GuildRaidID": "8",
    "NeedPoint": "86400000",
    "RewardID": "3702008"
  },
  {
    "ID": "79",
    "GuildRaidID": "8",
    "NeedPoint": "108000000",
    "RewardID": "3702009"
  },
  {
    "ID": "80",
    "GuildRaidID": "8",
    "NeedPoint": "144000000",
    "RewardID": "3702010"
  },
  {
    "ID": "81",
    "GuildRaidID": "9",
    "NeedPoint": "2310000",
    "RewardID": "3702001"
  },
  {
    "ID": "82",
    "GuildRaidID": "9",
    "NeedPoint": "7200000",
    "RewardID": "3702002"
  },
  {
    "ID": "83",
    "GuildRaidID": "9",
    "NeedPoint": "14400000",
    "RewardID": "3702003"
  },
  {
    "ID": "84",
    "GuildRaidID": "9",
    "NeedPoint": "28800000",
    "RewardID": "3702004"
  },
  {
    "ID": "85",
    "GuildRaidID": "9",
    "NeedPoint": "43200000",
    "RewardID": "3702005"
  },
  {
    "ID": "86",
    "GuildRaidID": "9",
    "NeedPoint": "57600000",
    "RewardID": "3702006"
  },
  {
    "ID": "87",
    "GuildRaidID": "9",
    "NeedPoint": "72000000",
    "RewardID": "3702007"
  },
  {
    "ID": "88",
    "GuildRaidID": "9",
    "NeedPoint": "86400000",
    "RewardID": "3702008"
  },
  {
    "ID": "89",
    "GuildRaidID": "9",
    "NeedPoint": "108000000",
    "RewardID": "3702009"
  },
  {
    "ID": "90",
    "GuildRaidID": "9",
    "NeedPoint": "144000000",
    "RewardID": "3702010"
  },
  {
    "ID": "91",
    "GuildRaidID": "10",
    "NeedPoint": "2310000",
    "RewardID": "3702001"
  },
  {
    "ID": "92",
    "GuildRaidID": "10",
    "NeedPoint": "7200000",
    "RewardID": "3702002"
  },
  {
    "ID": "93",
    "GuildRaidID": "10",
    "NeedPoint": "14400000",
    "RewardID": "3702003"
  },
  {
    "ID": "94",
    "GuildRaidID": "10",
    "NeedPoint": "28800000",
    "RewardID": "3702004"
  },
  {
    "ID": "95",
    "GuildRaidID": "10",
    "NeedPoint": "43200000",
    "RewardID": "3702005"
  },
  {
    "ID": "96",
    "GuildRaidID": "10",
    "NeedPoint": "57600000",
    "RewardID": "3702006"
  },
  {
    "ID": "97",
    "GuildRaidID": "10",
    "NeedPoint": "72000000",
    "RewardID": "3702007"
  },
  {
    "ID": "98",
    "GuildRaidID": "10",
    "NeedPoint": "86400000",
    "RewardID": "3702008"
  },
  {
    "ID": "99",
    "GuildRaidID": "10",
    "NeedPoint": "108000000",
    "RewardID": "3702009"
  },
  {
    "ID": "100",
    "GuildRaidID": "10",
    "NeedPoint": "144000000",
    "RewardID": "3702010"
  },
  {
    "ID": "101",
    "GuildRaidID": "11",
    "NeedPoint": "2310000",
    "RewardID": "3702001"
  },
  {
    "ID": "102",
    "GuildRaidID": "11",
    "NeedPoint": "7200000",
    "RewardID": "3702002"
  },
  {
    "ID": "103",
    "GuildRaidID": "11",
    "NeedPoint": "14400000",
    "RewardID": "3702003"
  },
  {
    "ID": "104",
    "GuildRaidID": "11",
    "NeedPoint": "28800000",
    "RewardID": "3702004"
  },
  {
    "ID": "105",
    "GuildRaidID": "11",
    "NeedPoint": "43200000",
    "RewardID": "3702005"
  },
  {
    "ID": "106",
    "GuildRaidID": "11",
    "NeedPoint": "57600000",
    "RewardID": "3702006"
  },
  {
    "ID": "107",
    "GuildRaidID": "11",
    "NeedPoint": "72000000",
    "RewardID": "3702007"
  },
  {
    "ID": "108",
    "GuildRaidID": "11",
    "NeedPoint": "86400000",
    "RewardID": "3702008"
  },
  {
    "ID": "109",
    "GuildRaidID": "11",
    "NeedPoint": "108000000",
    "RewardID": "3702009"
  },
  {
    "ID": "110",
    "GuildRaidID": "11",
    "NeedPoint": "144000000",
    "RewardID": "3702010"
  },
  {
    "ID": "111",
    "GuildRaidID": "12",
    "NeedPoint": "2310000",
    "RewardID": "3702001"
  },
  {
    "ID": "112",
    "GuildRaidID": "12",
    "NeedPoint": "7200000",
    "RewardID": "3702002"
  },
  {
    "ID": "113",
    "GuildRaidID": "12",
    "NeedPoint": "14400000",
    "RewardID": "3702003"
  },
  {
    "ID": "114",
    "GuildRaidID": "12",
    "NeedPoint": "28800000",
    "RewardID": "3702004"
  },
  {
    "ID": "115",
    "GuildRaidID": "12",
    "NeedPoint": "43200000",
    "RewardID": "3702005"
  },
  {
    "ID": "116",
    "GuildRaidID": "12",
    "NeedPoint": "57600000",
    "RewardID": "3702006"
  },
  {
    "ID": "117",
    "GuildRaidID": "12",
    "NeedPoint": "72000000",
    "RewardID": "3702007"
  },
  {
    "ID": "118",
    "GuildRaidID": "12",
    "NeedPoint": "86400000",
    "RewardID": "3702008"
  },
  {
    "ID": "119",
    "GuildRaidID": "12",
    "NeedPoint": "108000000",
    "RewardID": "3702009"
  },
  {
    "ID": "120",
    "GuildRaidID": "12",
    "NeedPoint": "144000000",
    "RewardID": "3702010"
  },
  {
    "ID": "121",
    "GuildRaidID": "13",
    "NeedPoint": "2310000",
    "RewardID": "3702001"
  },
  {
    "ID": "122",
    "GuildRaidID": "13",
    "NeedPoint": "7200000",
    "RewardID": "3702002"
  },
  {
    "ID": "123",
    "GuildRaidID": "13",
    "NeedPoint": "14400000",
    "RewardID": "3702003"
  },
  {
    "ID": "124",
    "GuildRaidID": "13",
    "NeedPoint": "28800000",
    "RewardID": "3702004"
  },
  {
    "ID": "125",
    "GuildRaidID": "13",
    "NeedPoint": "43200000",
    "RewardID": "3702005"
  },
  {
    "ID": "126",
    "GuildRaidID": "13",
    "NeedPoint": "57600000",
    "RewardID": "3702006"
  },
  {
    "ID": "127",
    "GuildRaidID": "13",
    "NeedPoint": "72000000",
    "RewardID": "3702007"
  },
  {
    "ID": "128",
    "GuildRaidID": "13",
    "NeedPoint": "86400000",
    "RewardID": "3702008"
  },
  {
    "ID": "129",
    "GuildRaidID": "13",
    "NeedPoint": "108000000",
    "RewardID": "3702009"
  },
  {
    "ID": "130",
    "GuildRaidID": "13",
    "NeedPoint": "144000000",
    "RewardID": "3702010"
  },
  {
    "ID": "131",
    "GuildRaidID": "14",
    "NeedPoint": "2310000",
    "RewardID": "3702001"
  },
  {
    "ID": "132",
    "GuildRaidID": "14",
    "NeedPoint": "7200000",
    "RewardID": "3702002"
  },
  {
    "ID": "133",
    "GuildRaidID": "14",
    "NeedPoint": "14400000",
    "RewardID": "3702003"
  },
  {
    "ID": "134",
    "GuildRaidID": "14",
    "NeedPoint": "28800000",
    "RewardID": "3702004"
  },
  {
    "ID": "135",
    "GuildRaidID": "14",
    "NeedPoint": "43200000",
    "RewardID": "3702005"
  },
  {
    "ID": "136",
    "GuildRaidID": "14",
    "NeedPoint": "57600000",
    "RewardID": "3702006"
  },
  {
    "ID": "137",
    "GuildRaidID": "14",
    "NeedPoint": "72000000",
    "RewardID": "3702007"
  },
  {
    "ID": "138",
    "GuildRaidID": "14",
    "NeedPoint": "86400000",
    "RewardID": "3702008"
  },
  {
    "ID": "139",
    "GuildRaidID": "14",
    "NeedPoint": "108000000",
    "RewardID": "3702009"
  },
  {
    "ID": "140",
    "GuildRaidID": "14",
    "NeedPoint": "144000000",
    "RewardID": "3702010"
  },
  {
    "ID": "141",
    "GuildRaidID": "15",
    "NeedPoint": "2310000",
    "RewardID": "3702001"
  },
  {
    "ID": "142",
    "GuildRaidID": "15",
    "NeedPoint": "7200000",
    "RewardID": "3702002"
  },
  {
    "ID": "143",
    "GuildRaidID": "15",
    "NeedPoint": "14400000",
    "RewardID": "3702003"
  },
  {
    "ID": "144",
    "GuildRaidID": "15",
    "NeedPoint": "28800000",
    "RewardID": "3702004"
  },
  {
    "ID": "145",
    "GuildRaidID": "15",
    "NeedPoint": "43200000",
    "RewardID": "3702005"
  },
  {
    "ID": "146",
    "GuildRaidID": "15",
    "NeedPoint": "57600000",
    "RewardID": "3702006"
  },
  {
    "ID": "147",
    "GuildRaidID": "15",
    "NeedPoint": "72000000",
    "RewardID": "3702007"
  },
  {
    "ID": "148",
    "GuildRaidID": "15",
    "NeedPoint": "86400000",
    "RewardID": "3702008"
  },
  {
    "ID": "149",
    "GuildRaidID": "15",
    "NeedPoint": "108000000",
    "RewardID": "3702009"
  },
  {
    "ID": "150",
    "GuildRaidID": "15",
    "NeedPoint": "144000000",
    "RewardID": "3702010"
  },
  {
    "ID": "151",
    "GuildRaidID": "16",
    "NeedPoint": "2310000",
    "RewardID": "3702001"
  },
  {
    "ID": "152",
    "GuildRaidID": "16",
    "NeedPoint": "7200000",
    "RewardID": "3702002"
  },
  {
    "ID": "153",
    "GuildRaidID": "16",
    "NeedPoint": "14400000",
    "RewardID": "3702003"
  },
  {
    "ID": "154",
    "GuildRaidID": "16",
    "NeedPoint": "28800000",
    "RewardID": "3702004"
  },
  {
    "ID": "155",
    "GuildRaidID": "16",
    "NeedPoint": "43200000",
    "RewardID": "3702005"
  },
  {
    "ID": "156",
    "GuildRaidID": "16",
    "NeedPoint": "57600000",
    "RewardID": "3702006"
  },
  {
    "ID": "157",
    "GuildRaidID": "16",
    "NeedPoint": "72000000",
    "RewardID": "3702007"
  },
  {
    "ID": "158",
    "GuildRaidID": "16",
    "NeedPoint": "86400000",
    "RewardID": "3702008"
  },
  {
    "ID": "159",
    "GuildRaidID": "16",
    "NeedPoint": "108000000",
    "RewardID": "3702009"
  },
  {
    "ID": "160",
    "GuildRaidID": "16",
    "NeedPoint": "144000000",
    "RewardID": "3702010"
  },
  {
    "ID": "161",
    "GuildRaidID": "17",
    "NeedPoint": "2310000",
    "RewardID": "3702001"
  },
  {
    "ID": "162",
    "GuildRaidID": "17",
    "NeedPoint": "7200000",
    "RewardID": "3702002"
  },
  {
    "ID": "163",
    "GuildRaidID": "17",
    "NeedPoint": "14400000",
    "RewardID": "3702003"
  },
  {
    "ID": "164",
    "GuildRaidID": "17",
    "NeedPoint": "28800000",
    "RewardID": "3702004"
  },
  {
    "ID": "165",
    "GuildRaidID": "17",
    "NeedPoint": "43200000",
    "RewardID": "3702005"
  },
  {
    "ID": "166",
    "GuildRaidID": "17",
    "NeedPoint": "57600000",
    "RewardID": "3702006"
  },
  {
    "ID": "167",
    "GuildRaidID": "17",
    "NeedPoint": "72000000",
    "RewardID": "3702007"
  },
  {
    "ID": "168",
    "GuildRaidID": "17",
    "NeedPoint": "86400000",
    "RewardID": "3702008"
  },
  {
    "ID": "169",
    "GuildRaidID": "17",
    "NeedPoint": "108000000",
    "RewardID": "3702009"
  },
  {
    "ID": "170",
    "GuildRaidID": "17",
    "NeedPoint": "144000000",
    "RewardID": "3702010"
  },
  {
    "ID": "171",
    "GuildRaidID": "18",
    "NeedPoint": "2310000",
    "RewardID": "3702001"
  },
  {
    "ID": "172",
    "GuildRaidID": "18",
    "NeedPoint": "7200000",
    "RewardID": "3702002"
  },
  {
    "ID": "173",
    "GuildRaidID": "18",
    "NeedPoint": "14400000",
    "RewardID": "3702003"
  },
  {
    "ID": "174",
    "GuildRaidID": "18",
    "NeedPoint": "28800000",
    "RewardID": "3702004"
  },
  {
    "ID": "175",
    "GuildRaidID": "18",
    "NeedPoint": "43200000",
    "RewardID": "3702005"
  },
  {
    "ID": "176",
    "GuildRaidID": "18",
    "NeedPoint": "57600000",
    "RewardID": "3702006"
  },
  {
    "ID": "177",
    "GuildRaidID": "18",
    "NeedPoint": "72000000",
    "RewardID": "3702007"
  },
  {
    "ID": "178",
    "GuildRaidID": "18",
    "NeedPoint": "86400000",
    "RewardID": "3702008"
  },
  {
    "ID": "179",
    "GuildRaidID": "18",
    "NeedPoint": "108000000",
    "RewardID": "3702009"
  },
  {
    "ID": "180",
    "GuildRaidID": "18",
    "NeedPoint": "144000000",
    "RewardID": "3702010"
  },
  {
    "ID": "181",
    "GuildRaidID": "19",
    "NeedPoint": "2310000",
    "RewardID": "3702001"
  },
  {
    "ID": "182",
    "GuildRaidID": "19",
    "NeedPoint": "7200000",
    "RewardID": "3702002"
  },
  {
    "ID": "183",
    "GuildRaidID": "19",
    "NeedPoint": "14400000",
    "RewardID": "3702003"
  },
  {
    "ID": "184",
    "GuildRaidID": "19",
    "NeedPoint": "28800000",
    "RewardID": "3702004"
  },
  {
    "ID": "185",
    "GuildRaidID": "19",
    "NeedPoint": "43200000",
    "RewardID": "3702005"
  },
  {
    "ID": "186",
    "GuildRaidID": "19",
    "NeedPoint": "57600000",
    "RewardID": "3702006"
  },
  {
    "ID": "187",
    "GuildRaidID": "19",
    "NeedPoint": "72000000",
    "RewardID": "3702007"
  },
  {
    "ID": "188",
    "GuildRaidID": "19",
    "NeedPoint": "86400000",
    "RewardID": "3702008"
  },
  {
    "ID": "189",
    "GuildRaidID": "19",
    "NeedPoint": "108000000",
    "RewardID": "3702009"
  },
  {
    "ID": "190",
    "GuildRaidID": "19",
    "NeedPoint": "144000000",
    "RewardID": "3702010"
  },
  {
    "ID": "191",
    "GuildRaidID": "30",
    "NeedPoint": "800000",
    "RewardID": "3702001"
  },
  {
    "ID": "192",
    "GuildRaidID": "30",
    "NeedPoint": "2500000",
    "RewardID": "3702002"
  },
  {
    "ID": "193",
    "GuildRaidID": "30",
    "NeedPoint": "5000000",
    "RewardID": "3702003"
  },
  {
    "ID": "194",
    "GuildRaidID": "30",
    "NeedPoint": "10000000",
    "RewardID": "3702004"
  },
  {
    "ID": "195",
    "GuildRaidID": "30",
    "NeedPoint": "15000000",
    "RewardID": "3702005"
  },
  {
    "ID": "196",
    "GuildRaidID": "30",
    "NeedPoint": "20000000",
    "RewardID": "3702006"
  },
  {
    "ID": "197",
    "GuildRaidID": "30",
    "NeedPoint": "25000000",
    "RewardID": "3702007"
  },
  {
    "ID": "198",
    "GuildRaidID": "30",
    "NeedPoint": "30000000",
    "RewardID": "3702008"
  },
  {
    "ID": "199",
    "GuildRaidID": "30",
    "NeedPoint": "37500000",
    "RewardID": "3702009"
  },
  {
    "ID": "200",
    "GuildRaidID": "30",
    "NeedPoint": "50000000",
    "RewardID": "3702010"
  },
  {
    "ID": "201",
    "GuildRaidID": "31",
    "NeedPoint": "800000",
    "RewardID": "3702001"
  },
  {
    "ID": "202",
    "GuildRaidID": "31",
    "NeedPoint": "2500000",
    "RewardID": "3702002"
  },
  {
    "ID": "203",
    "GuildRaidID": "31",
    "NeedPoint": "5000000",
    "RewardID": "3702003"
  },
  {
    "ID": "204",
    "GuildRaidID": "31",
    "NeedPoint": "10000000",
    "RewardID": "3702004"
  },
  {
    "ID": "205",
    "GuildRaidID": "31",
    "NeedPoint": "15000000",
    "RewardID": "3702005"
  },
  {
    "ID": "206",
    "GuildRaidID": "31",
    "NeedPoint": "20000000",
    "RewardID": "3702006"
  },
  {
    "ID": "207",
    "GuildRaidID": "31",
    "NeedPoint": "25000000",
    "RewardID": "3702007"
  },
  {
    "ID": "208",
    "GuildRaidID": "31",
    "NeedPoint": "30000000",
    "RewardID": "3702008"
  },
  {
    "ID": "209",
    "GuildRaidID": "31",
    "NeedPoint": "37500000",
    "RewardID": "3702009"
  },
  {
    "ID": "210",
    "GuildRaidID": "31",
    "NeedPoint": "50000000",
    "RewardID": "3702010"
  },
  {
    "ID": "211",
    "GuildRaidID": "32",
    "NeedPoint": "800000",
    "RewardID": "3702001"
  },
  {
    "ID": "212",
    "GuildRaidID": "32",
    "NeedPoint": "2500000",
    "RewardID": "3702002"
  },
  {
    "ID": "213",
    "GuildRaidID": "32",
    "NeedPoint": "5000000",
    "RewardID": "3702003"
  },
  {
    "ID": "214",
    "GuildRaidID": "32",
    "NeedPoint": "10000000",
    "RewardID": "3702004"
  },
  {
    "ID": "215",
    "GuildRaidID": "32",
    "NeedPoint": "15000000",
    "RewardID": "3702005"
  },
  {
    "ID": "216",
    "GuildRaidID": "32",
    "NeedPoint": "20000000",
    "RewardID": "3702006"
  },
  {
    "ID": "217",
    "GuildRaidID": "32",
    "NeedPoint": "25000000",
    "RewardID": "3702007"
  },
  {
    "ID": "218",
    "GuildRaidID": "32",
    "NeedPoint": "30000000",
    "RewardID": "3702008"
  },
  {
    "ID": "219",
    "GuildRaidID": "32",
    "NeedPoint": "37500000",
    "RewardID": "3702009"
  },
  {
    "ID": "220",
    "GuildRaidID": "32",
    "NeedPoint": "50000000",
    "RewardID": "3702010"
  },
  {
    "ID": "221",
    "GuildRaidID": "33",
    "NeedPoint": "800000",
    "RewardID": "3702001"
  },
  {
    "ID": "222",
    "GuildRaidID": "33",
    "NeedPoint": "2500000",
    "RewardID": "3702002"
  },
  {
    "ID": "223",
    "GuildRaidID": "33",
    "NeedPoint": "5000000",
    "RewardID": "3702003"
  },
  {
    "ID": "224",
    "GuildRaidID": "33",
    "NeedPoint": "10000000",
    "RewardID": "3702004"
  },
  {
    "ID": "225",
    "GuildRaidID": "33",
    "NeedPoint": "15000000",
    "RewardID": "3702005"
  },
  {
    "ID": "226",
    "GuildRaidID": "33",
    "NeedPoint": "20000000",
    "RewardID": "3702006"
  },
  {
    "ID": "227",
    "GuildRaidID": "33",
    "NeedPoint": "25000000",
    "RewardID": "3702007"
  },
  {
    "ID": "228",
    "GuildRaidID": "33",
    "NeedPoint": "30000000",
    "RewardID": "3702008"
  },
  {
    "ID": "229",
    "GuildRaidID": "33",
    "NeedPoint": "37500000",
    "RewardID": "3702009"
  },
  {
    "ID": "230",
    "GuildRaidID": "33",
    "NeedPoint": "50000000",
    "RewardID": "3702010"
  },
  {
    "ID": "231",
    "GuildRaidID": "34",
    "NeedPoint": "800000",
    "RewardID": "3702001"
  },
  {
    "ID": "232",
    "GuildRaidID": "34",
    "NeedPoint": "2500000",
    "RewardID": "3702002"
  },
  {
    "ID": "233",
    "GuildRaidID": "34",
    "NeedPoint": "5000000",
    "RewardID": "3702003"
  },
  {
    "ID": "234",
    "GuildRaidID": "34",
    "NeedPoint": "10000000",
    "RewardID": "3702004"
  },
  {
    "ID": "235",
    "GuildRaidID": "34",
    "NeedPoint": "15000000",
    "RewardID": "3702005"
  },
  {
    "ID": "236",
    "GuildRaidID": "34",
    "NeedPoint": "20000000",
    "RewardID": "3702006"
  },
  {
    "ID": "237",
    "GuildRaidID": "34",
    "NeedPoint": "25000000",
    "RewardID": "3702007"
  },
  {
    "ID": "238",
    "GuildRaidID": "34",
    "NeedPoint": "30000000",
    "RewardID": "3702008"
  },
  {
    "ID": "239",
    "GuildRaidID": "34",
    "NeedPoint": "37500000",
    "RewardID": "3702009"
  },
  {
    "ID": "240",
    "GuildRaidID": "34",
    "NeedPoint": "50000000",
    "RewardID": "3702010"
  },
  {
    "ID": "241",
    "GuildRaidID": "35",
    "NeedPoint": "800000",
    "RewardID": "3702001"
  },
  {
    "ID": "242",
    "GuildRaidID": "35",
    "NeedPoint": "2500000",
    "RewardID": "3702002"
  },
  {
    "ID": "243",
    "GuildRaidID": "35",
    "NeedPoint": "5000000",
    "RewardID": "3702003"
  },
  {
    "ID": "244",
    "GuildRaidID": "35",
    "NeedPoint": "10000000",
    "RewardID": "3702004"
  },
  {
    "ID": "245",
    "GuildRaidID": "35",
    "NeedPoint": "15000000",
    "RewardID": "3702005"
  },
  {
    "ID": "246",
    "GuildRaidID": "35",
    "NeedPoint": "20000000",
    "RewardID": "3702006"
  },
  {
    "ID": "247",
    "GuildRaidID": "35",
    "NeedPoint": "25000000",
    "RewardID": "3702007"
  },
  {
    "ID": "248",
    "GuildRaidID": "35",
    "NeedPoint": "30000000",
    "RewardID": "3702008"
  },
  {
    "ID": "249",
    "GuildRaidID": "35",
    "NeedPoint": "37500000",
    "RewardID": "3702009"
  },
  {
    "ID": "250",
    "GuildRaidID": "35",
    "NeedPoint": "50000000",
    "RewardID": "3702010"
  },
  {
    "ID": "251",
    "GuildRaidID": "36",
    "NeedPoint": "800000",
    "RewardID": "3702001"
  },
  {
    "ID": "252",
    "GuildRaidID": "36",
    "NeedPoint": "2500000",
    "RewardID": "3702002"
  },
  {
    "ID": "253",
    "GuildRaidID": "36",
    "NeedPoint": "5000000",
    "RewardID": "3702003"
  },
  {
    "ID": "254",
    "GuildRaidID": "36",
    "NeedPoint": "10000000",
    "RewardID": "3702004"
  },
  {
    "ID": "255",
    "GuildRaidID": "36",
    "NeedPoint": "15000000",
    "RewardID": "3702005"
  },
  {
    "ID": "256",
    "GuildRaidID": "36",
    "NeedPoint": "20000000",
    "RewardID": "3702006"
  },
  {
    "ID": "257",
    "GuildRaidID": "36",
    "NeedPoint": "25000000",
    "RewardID": "3702007"
  },
  {
    "ID": "258",
    "GuildRaidID": "36",
    "NeedPoint": "30000000",
    "RewardID": "3702008"
  },
  {
    "ID": "259",
    "GuildRaidID": "36",
    "NeedPoint": "37500000",
    "RewardID": "3702009"
  },
  {
    "ID": "260",
    "GuildRaidID": "36",
    "NeedPoint": "50000000",
    "RewardID": "3702010"
  },
  {
    "ID": "261",
    "GuildRaidID": "37",
    "NeedPoint": "800000",
    "RewardID": "3702001"
  },
  {
    "ID": "262",
    "GuildRaidID": "37",
    "NeedPoint": "2500000",
    "RewardID": "3702002"
  },
  {
    "ID": "263",
    "GuildRaidID": "37",
    "NeedPoint": "5000000",
    "RewardID": "3702003"
  },
  {
    "ID": "264",
    "GuildRaidID": "37",
    "NeedPoint": "10000000",
    "RewardID": "3702004"
  },
  {
    "ID": "265",
    "GuildRaidID": "37",
    "NeedPoint": "15000000",
    "RewardID": "3702005"
  },
  {
    "ID": "266",
    "GuildRaidID": "37",
    "NeedPoint": "20000000",
    "RewardID": "3702006"
  },
  {
    "ID": "267",
    "GuildRaidID": "37",
    "NeedPoint": "25000000",
    "RewardID": "3702007"
  },
  {
    "ID": "268",
    "GuildRaidID": "37",
    "NeedPoint": "30000000",
    "RewardID": "3702008"
  },
  {
    "ID": "269",
    "GuildRaidID": "37",
    "NeedPoint": "37500000",
    "RewardID": "3702009"
  },
  {
    "ID": "270",
    "GuildRaidID": "37",
    "NeedPoint": "50000000",
    "RewardID": "3702010"
  },
  {
    "ID": "271",
    "GuildRaidID": "38",
    "NeedPoint": "800000",
    "RewardID": "3702001"
  },
  {
    "ID": "272",
    "GuildRaidID": "38",
    "NeedPoint": "2500000",
    "RewardID": "3702002"
  },
  {
    "ID": "273",
    "GuildRaidID": "38",
    "NeedPoint": "5000000",
    "RewardID": "3702003"
  },
  {
    "ID": "274",
    "GuildRaidID": "38",
    "NeedPoint": "10000000",
    "RewardID": "3702004"
  },
  {
    "ID": "275",
    "GuildRaidID": "38",
    "NeedPoint": "15000000",
    "RewardID": "3702005"
  },
  {
    "ID": "276",
    "GuildRaidID": "38",
    "NeedPoint": "20000000",
    "RewardID": "3702006"
  },
  {
    "ID": "277",
    "GuildRaidID": "38",
    "NeedPoint": "25000000",
    "RewardID": "3702007"
  },
  {
    "ID": "278",
    "GuildRaidID": "38",
    "NeedPoint": "30000000",
    "RewardID": "3702008"
  },
  {
    "ID": "279",
    "GuildRaidID": "38",
    "NeedPoint": "37500000",
    "RewardID": "3702009"
  },
  {
    "ID": "280",
    "GuildRaidID": "38",
    "NeedPoint": "50000000",
    "RewardID": "3702010"
  },
  {
    "ID": "281",
    "GuildRaidID": "39",
    "NeedPoint": "800000",
    "RewardID": "3702001"
  },
  {
    "ID": "282",
    "GuildRaidID": "39",
    "NeedPoint": "2500000",
    "RewardID": "3702002"
  },
  {
    "ID": "283",
    "GuildRaidID": "39",
    "NeedPoint": "5000000",
    "RewardID": "3702003"
  },
  {
    "ID": "284",
    "GuildRaidID": "39",
    "NeedPoint": "10000000",
    "RewardID": "3702004"
  },
  {
    "ID": "285",
    "GuildRaidID": "39",
    "NeedPoint": "15000000",
    "RewardID": "3702005"
  },
  {
    "ID": "286",
    "GuildRaidID": "39",
    "NeedPoint": "20000000",
    "RewardID": "3702006"
  },
  {
    "ID": "287",
    "GuildRaidID": "39",
    "NeedPoint": "25000000",
    "RewardID": "3702007"
  },
  {
    "ID": "288",
    "GuildRaidID": "39",
    "NeedPoint": "30000000",
    "RewardID": "3702008"
  },
  {
    "ID": "289",
    "GuildRaidID": "39",
    "NeedPoint": "37500000",
    "RewardID": "3702009"
  },
  {
    "ID": "290",
    "GuildRaidID": "39",
    "NeedPoint": "50000000",
    "RewardID": "3702010"
  },
  {
    "ID": "291",
    "GuildRaidID": "40",
    "NeedPoint": "800000",
    "RewardID": "3702001"
  },
  {
    "ID": "292",
    "GuildRaidID": "40",
    "NeedPoint": "2500000",
    "RewardID": "3702002"
  },
  {
    "ID": "293",
    "GuildRaidID": "40",
    "NeedPoint": "5000000",
    "RewardID": "3702003"
  },
  {
    "ID": "294",
    "GuildRaidID": "40",
    "NeedPoint": "10000000",
    "RewardID": "3702004"
  },
  {
    "ID": "295",
    "GuildRaidID": "40",
    "NeedPoint": "15000000",
    "RewardID": "3702005"
  },
  {
    "ID": "296",
    "GuildRaidID": "40",
    "NeedPoint": "20000000",
    "RewardID": "3702006"
  },
  {
    "ID": "297",
    "GuildRaidID": "40",
    "NeedPoint": "25000000",
    "RewardID": "3702007"
  },
  {
    "ID": "298",
    "GuildRaidID": "40",
    "NeedPoint": "30000000",
    "RewardID": "3702008"
  },
  {
    "ID": "299",
    "GuildRaidID": "40",
    "NeedPoint": "37500000",
    "RewardID": "3702009"
  },
  {
    "ID": "300",
    "GuildRaidID": "40",
    "NeedPoint": "50000000",
    "NeedPoint_fallback1": "3702010"
  }
]